setup.py
sentry_datadog_helpers/__init__.py
sentry_datadog_helpers.egg-info/PKG-INFO
sentry_datadog_helpers.egg-info/SOURCES.txt
sentry_datadog_helpers.egg-info/dependency_links.txt
sentry_datadog_helpers.egg-info/not-zip-safe
sentry_datadog_helpers.egg-info/requires.txt
sentry_datadog_helpers.egg-info/top_level.txt
sentry_datadog_helpers/raven/__init__.py
sentry_datadog_helpers/raven/processors.py
sentry_datadog_helpers/sentry/__init__.py
sentry_datadog_helpers/sentry/plugins/__init__.py
sentry_datadog_helpers/sentry/plugins/sentry_datadog/__init__.py
sentry_datadog_helpers/sentry/plugins/sentry_datadog/models.py
sentry_datadog_helpers/test/__init__.py
sentry_datadog_helpers/test/test_processors.py
sentry_datadog_helpers/test/test_sentry_datadog_helpers.py
sentry_datadog_helpers/test/utils.py