Metadata-Version: 1.1
Name: sentry-datadog-helpers
Version: 1.4.0
Summary: Suite of Sentry tools which enhance integrations with Datadog.
Home-page: http://github.com/ewdurbin/sentry-datadog-helpers
Author: Ernest W. Durbin III
Author-email: ewdurbin@gmail.com
License: BSD
Download-URL: https://pypi.python.org/pypi/sentry-datadog-helpers
Platform: UNKNOWN
Classifier: Intended Audience :: Developers
Classifier: Intended Audience :: System Administrators
Classifier: Operating System :: OS Independent
Classifier: Topic :: Software Development
